{
  "id": "c2576c39-474b-42f5-8781-e90aefbaee48",
  "prevId": "00000000-0000-0000-0000-000000000000",
  "version": "7",
  "dialect": "postgresql",
  "tables": {
    "public.agency_configs": {
      "name": "agency_configs",
      "schema": "",
      "columns": {
        "id": {
          "name": "id",
          "type": "serial",
          "primaryKey": true,
          "notNull": true
        },
        "user_id": {
          "name": "user_id",
          "type": "text",
          "primaryKey": false,
          "notNull": true
        },
        "slug": {
          "name": "slug",
          "type": "text",
          "primaryKey": false,
          "notNull": true
        },
        "name": {
          "name": "name",
          "type": "text",
          "primaryKey": false,
          "notNull": true
        },
        "industry": {
          "name": "industry",
          "type": "text",
          "primaryKey": false,
          "notNull": true
        },
        "description": {
          "name": "description",
          "type": "text",
          "primaryKey": false,
          "notNull": true
        },
        "onboarding_goal": {
          "name": "onboarding_goal",
          "type": "text",
          "primaryKey": false,
          "notNull": true
        },
        "tone": {
          "name": "tone",
          "type": "text",
          "primaryKey": false,
          "notNull": true
        },
        "target_audience": {
          "name": "target_audience",
          "type": "text",
          "primaryKey": false,
          "notNull": true
        },
        "max_questions": {
          "name": "max_questions",
          "type": "integer",
          "primaryKey": false,
          "notNull": true,
          "default": 8
        },
        "primary_color": {
          "name": "primary_color",
          "type": "text",
          "primaryKey": false,
          "notNull": true,
          "default": "'#4f46e5'"
        },
        "background_color": {
          "name": "background_color",
          "type": "text",
          "primaryKey": false,
          "notNull": true,
          "default": "'#ffffff'"
        },
        "text_color": {
          "name": "text_color",
          "type": "text",
          "primaryKey": false,
          "notNull": true,
          "default": "'#111827'"
        },
        "created_at": {
          "name": "created_at",
          "type": "timestamp",
          "primaryKey": false,
          "notNull": true,
          "default": "now()"
        },
        "updated_at": {
          "name": "updated_at",
          "type": "timestamp",
          "primaryKey": false,
          "notNull": true,
          "default": "now()"
        }
      },
      "indexes": {
        "agency_configs_user_id_idx": {
          "name": "agency_configs_user_id_idx",
          "columns": [
            {
              "expression": "user_id",
              "isExpression": false,
              "asc": true,
              "nulls": "last"
            }
          ],
          "isUnique": true,
          "concurrently": false,
          "method": "btree",
          "with": {}
        },
        "agency_configs_slug_idx": {
          "name": "agency_configs_slug_idx",
          "columns": [
            {
              "expression": "slug",
              "isExpression": false,
              "asc": true,
              "nulls": "last"
            }
          ],
          "isUnique": true,
          "concurrently": false,
          "method": "btree",
          "with": {}
        }
      },
      "foreignKeys": {
        "agency_configs_user_id_users_id_fk": {
          "name": "agency_configs_user_id_users_id_fk",
          "tableFrom": "agency_configs",
          "tableTo": "users",
          "columnsFrom": [
            "user_id"
          ],
          "columnsTo": [
            "id"
          ],
          "onDelete": "cascade",
          "onUpdate": "no action"
        }
      },
      "compositePrimaryKeys": {},
      "uniqueConstraints": {
        "agency_configs_slug_unique": {
          "name": "agency_configs_slug_unique",
          "nullsNotDistinct": false,
          "columns": [
            "slug"
          ]
        }
      },
      "policies": {},
      "checkConstraints": {},
      "isRLSEnabled": false
    },
    "public.answers": {
      "name": "answers",
      "schema": "",
      "columns": {
        "id": {
          "name": "id",
          "type": "serial",
          "primaryKey": true,
          "notNull": true
        },
        "submission_id": {
          "name": "submission_id",
          "type": "text",
          "primaryKey": false,
          "notNull": true
        },
        "question_id": {
          "name": "question_id",
          "type": "text",
          "primaryKey": false,
          "notNull": true
        },
        "question_text": {
          "name": "question_text",
          "type": "text",
          "primaryKey": false,
          "notNull": true
        },
        "value": {
          "name": "value",
          "type": "jsonb",
          "primaryKey": false,
          "notNull": true
        },
        "created_at": {
          "name": "created_at",
          "type": "timestamp",
          "primaryKey": false,
          "notNull": true,
          "default": "now()"
        }
      },
      "indexes": {
        "answers_submission_id_idx": {
          "name": "answers_submission_id_idx",
          "columns": [
            {
              "expression": "submission_id",
              "isExpression": false,
              "asc": true,
              "nulls": "last"
            }
          ],
          "isUnique": false,
          "concurrently": false,
          "method": "btree",
          "with": {}
        }
      },
      "foreignKeys": {
        "answers_submission_id_submissions_id_fk": {
          "name": "answers_submission_id_submissions_id_fk",
          "tableFrom": "answers",
          "tableTo": "submissions",
          "columnsFrom": [
            "submission_id"
          ],
          "columnsTo": [
            "id"
          ],
          "onDelete": "cascade",
          "onUpdate": "no action"
        }
      },
      "compositePrimaryKeys": {},
      "uniqueConstraints": {},
      "policies": {},
      "checkConstraints": {},
      "isRLSEnabled": false
    },
    "public.call_sessions": {
      "name": "call_sessions",
      "schema": "",
      "columns": {
        "id": {
          "name": "id",
          "type": "text",
          "primaryKey": true,
          "notNull": true
        },
        "user_id": {
          "name": "user_id",
          "type": "text",
          "primaryKey": false,
          "notNull": true
        },
        "agency_config_id": {
          "name": "agency_config_id",
          "type": "integer",
          "primaryKey": false,
          "notNull": false
        },
        "client_name": {
          "name": "client_name",
          "type": "text",
          "primaryKey": false,
          "notNull": false
        },
        "client_email": {
          "name": "client_email",
          "type": "text",
          "primaryKey": false,
          "notNull": false
        },
        "meeting_url": {
          "name": "meeting_url",
          "type": "text",
          "primaryKey": false,
          "notNull": false
        },
        "status": {
          "name": "status",
          "type": "text",
          "primaryKey": false,
          "notNull": true,
          "default": "'active'"
        },
        "started_at": {
          "name": "started_at",
          "type": "timestamp",
          "primaryKey": false,
          "notNull": true,
          "default": "now()"
        },
        "ended_at": {
          "name": "ended_at",
          "type": "timestamp",
          "primaryKey": false,
          "notNull": false
        },
        "duration": {
          "name": "duration",
          "type": "integer",
          "primaryKey": false,
          "notNull": false
        },
        "summary": {
          "name": "summary",
          "type": "text",
          "primaryKey": false,
          "notNull": false
        },
        "created_at": {
          "name": "created_at",
          "type": "timestamp",
          "primaryKey": false,
          "notNull": true,
          "default": "now()"
        },
        "updated_at": {
          "name": "updated_at",
          "type": "timestamp",
          "primaryKey": false,
          "notNull": true,
          "default": "now()"
        }
      },
      "indexes": {
        "call_sessions_user_id_idx": {
          "name": "call_sessions_user_id_idx",
          "columns": [
            {
              "expression": "user_id",
              "isExpression": false,
              "asc": true,
              "nulls": "last"
            }
          ],
          "isUnique": false,
          "concurrently": false,
          "method": "btree",
          "with": {}
        },
        "call_sessions_status_idx": {
          "name": "call_sessions_status_idx",
          "columns": [
            {
              "expression": "status",
              "isExpression": false,
              "asc": true,
              "nulls": "last"
            }
          ],
          "isUnique": false,
          "concurrently": false,
          "method": "btree",
          "with": {}
        },
        "call_sessions_started_at_idx": {
          "name": "call_sessions_started_at_idx",
          "columns": [
            {
              "expression": "started_at",
              "isExpression": false,
              "asc": true,
              "nulls": "last"
            }
          ],
          "isUnique": false,
          "concurrently": false,
          "method": "btree",
          "with": {}
        }
      },
      "foreignKeys": {
        "call_sessions_user_id_users_id_fk": {
          "name": "call_sessions_user_id_users_id_fk",
          "tableFrom": "call_sessions",
          "tableTo": "users",
          "columnsFrom": [
            "user_id"
          ],
          "columnsTo": [
            "id"
          ],
          "onDelete": "cascade",
          "onUpdate": "no action"
        },
        "call_sessions_agency_config_id_agency_configs_id_fk": {
          "name": "call_sessions_agency_config_id_agency_configs_id_fk",
          "tableFrom": "call_sessions",
          "tableTo": "agency_configs",
          "columnsFrom": [
            "agency_config_id"
          ],
          "columnsTo": [
            "id"
          ],
          "onDelete": "set null",
          "onUpdate": "no action"
        }
      },
      "compositePrimaryKeys": {},
      "uniqueConstraints": {},
      "policies": {},
      "checkConstraints": {},
      "isRLSEnabled": false
    },
    "public.checklist_completions": {
      "name": "checklist_completions",
      "schema": "",
      "columns": {
        "id": {
          "name": "id",
          "type": "serial",
          "primaryKey": true,
          "notNull": true
        },
        "call_session_id": {
          "name": "call_session_id",
          "type": "text",
          "primaryKey": false,
          "notNull": true
        },
        "checklist_item_id": {
          "name": "checklist_item_id",
          "type": "integer",
          "primaryKey": false,
          "notNull": true
        },
        "completed_at": {
          "name": "completed_at",
          "type": "timestamp",
          "primaryKey": false,
          "notNull": true
        },
        "extracted_info": {
          "name": "extracted_info",
          "type": "text",
          "primaryKey": false,
          "notNull": false
        },
        "transcript_segment_id": {
          "name": "transcript_segment_id",
          "type": "integer",
          "primaryKey": false,
          "notNull": false
        },
        "manually_marked": {
          "name": "manually_marked",
          "type": "boolean",
          "primaryKey": false,
          "notNull": true,
          "default": false
        }
      },
      "indexes": {
        "checklist_completions_call_session_id_idx": {
          "name": "checklist_completions_call_session_id_idx",
          "columns": [
            {
              "expression": "call_session_id",
              "isExpression": false,
              "asc": true,
              "nulls": "last"
            }
          ],
          "isUnique": false,
          "concurrently": false,
          "method": "btree",
          "with": {}
        }
      },
      "foreignKeys": {
        "checklist_completions_call_session_id_call_sessions_id_fk": {
          "name": "checklist_completions_call_session_id_call_sessions_id_fk",
          "tableFrom": "checklist_completions",
          "tableTo": "call_sessions",
          "columnsFrom": [
            "call_session_id"
          ],
          "columnsTo": [
            "id"
          ],
          "onDelete": "cascade",
          "onUpdate": "no action"
        },
        "checklist_completions_checklist_item_id_checklist_items_id_fk": {
          "name": "checklist_completions_checklist_item_id_checklist_items_id_fk",
          "tableFrom": "checklist_completions",
          "tableTo": "checklist_items",
          "columnsFrom": [
            "checklist_item_id"
          ],
          "columnsTo": [
            "id"
          ],
          "onDelete": "cascade",
          "onUpdate": "no action"
        },
        "checklist_completions_transcript_segment_id_transcript_segments_id_fk": {
          "name": "checklist_completions_transcript_segment_id_transcript_segments_id_fk",
          "tableFrom": "checklist_completions",
          "tableTo": "transcript_segments",
          "columnsFrom": [
            "transcript_segment_id"
          ],
          "columnsTo": [
            "id"
          ],
          "onDelete": "no action",
          "onUpdate": "no action"
        }
      },
      "compositePrimaryKeys": {},
      "uniqueConstraints": {},
      "policies": {},
      "checkConstraints": {},
      "isRLSEnabled": false
    },
    "public.checklist_items": {
      "name": "checklist_items",
      "schema": "",
      "columns": {
        "id": {
          "name": "id",
          "type": "serial",
          "primaryKey": true,
          "notNull": true
        },
        "agency_config_id": {
          "name": "agency_config_id",
          "type": "integer",
          "primaryKey": false,
          "notNull": true
        },
        "label": {
          "name": "label",
          "type": "text",
          "primaryKey": false,
          "notNull": true
        },
        "description": {
          "name": "description",
          "type": "text",
          "primaryKey": false,
          "notNull": false
        },
        "category": {
          "name": "category",
          "type": "text",
          "primaryKey": false,
          "notNull": false
        },
        "order": {
          "name": "order",
          "type": "integer",
          "primaryKey": false,
          "notNull": true
        },
        "required": {
          "name": "required",
          "type": "boolean",
          "primaryKey": false,
          "notNull": true,
          "default": true
        },
        "created_at": {
          "name": "created_at",
          "type": "timestamp",
          "primaryKey": false,
          "notNull": true,
          "default": "now()"
        }
      },
      "indexes": {
        "checklist_items_agency_config_id_idx": {
          "name": "checklist_items_agency_config_id_idx",
          "columns": [
            {
              "expression": "agency_config_id",
              "isExpression": false,
              "asc": true,
              "nulls": "last"
            }
          ],
          "isUnique": false,
          "concurrently": false,
          "method": "btree",
          "with": {}
        }
      },
      "foreignKeys": {
        "checklist_items_agency_config_id_agency_configs_id_fk": {
          "name": "checklist_items_agency_config_id_agency_configs_id_fk",
          "tableFrom": "checklist_items",
          "tableTo": "agency_configs",
          "columnsFrom": [
            "agency_config_id"
          ],
          "columnsTo": [
            "id"
          ],
          "onDelete": "cascade",
          "onUpdate": "no action"
        }
      },
      "compositePrimaryKeys": {},
      "uniqueConstraints": {},
      "policies": {},
      "checkConstraints": {},
      "isRLSEnabled": false
    },
    "public.question_prompts": {
      "name": "question_prompts",
      "schema": "",
      "columns": {
        "id": {
          "name": "id",
          "type": "serial",
          "primaryKey": true,
          "notNull": true
        },
        "call_session_id": {
          "name": "call_session_id",
          "type": "text",
          "primaryKey": false,
          "notNull": true
        },
        "prompt": {
          "name": "prompt",
          "type": "text",
          "primaryKey": false,
          "notNull": true
        },
        "category": {
          "name": "category",
          "type": "text",
          "primaryKey": false,
          "notNull": false
        },
        "suggested": {
          "name": "suggested",
          "type": "boolean",
          "primaryKey": false,
          "notNull": true,
          "default": true
        },
        "used_by_agent": {
          "name": "used_by_agent",
          "type": "boolean",
          "primaryKey": false,
          "notNull": true,
          "default": false
        },
        "created_at": {
          "name": "created_at",
          "type": "timestamp",
          "primaryKey": false,
          "notNull": true,
          "default": "now()"
        }
      },
      "indexes": {
        "question_prompts_call_session_id_idx": {
          "name": "question_prompts_call_session_id_idx",
          "columns": [
            {
              "expression": "call_session_id",
              "isExpression": false,
              "asc": true,
              "nulls": "last"
            }
          ],
          "isUnique": false,
          "concurrently": false,
          "method": "btree",
          "with": {}
        }
      },
      "foreignKeys": {
        "question_prompts_call_session_id_call_sessions_id_fk": {
          "name": "question_prompts_call_session_id_call_sessions_id_fk",
          "tableFrom": "question_prompts",
          "tableTo": "call_sessions",
          "columnsFrom": [
            "call_session_id"
          ],
          "columnsTo": [
            "id"
          ],
          "onDelete": "cascade",
          "onUpdate": "no action"
        }
      },
      "compositePrimaryKeys": {},
      "uniqueConstraints": {},
      "policies": {},
      "checkConstraints": {},
      "isRLSEnabled": false
    },
    "public.submissions": {
      "name": "submissions",
      "schema": "",
      "columns": {
        "id": {
          "name": "id",
          "type": "text",
          "primaryKey": true,
          "notNull": true
        },
        "user_id": {
          "name": "user_id",
          "type": "text",
          "primaryKey": false,
          "notNull": true
        },
        "client_name": {
          "name": "client_name",
          "type": "text",
          "primaryKey": false,
          "notNull": false
        },
        "summary": {
          "name": "summary",
          "type": "text",
          "primaryKey": false,
          "notNull": true
        },
        "created_at": {
          "name": "created_at",
          "type": "timestamp",
          "primaryKey": false,
          "notNull": true,
          "default": "now()"
        }
      },
      "indexes": {
        "submissions_user_id_idx": {
          "name": "submissions_user_id_idx",
          "columns": [
            {
              "expression": "user_id",
              "isExpression": false,
              "asc": true,
              "nulls": "last"
            }
          ],
          "isUnique": false,
          "concurrently": false,
          "method": "btree",
          "with": {}
        },
        "submissions_created_at_idx": {
          "name": "submissions_created_at_idx",
          "columns": [
            {
              "expression": "created_at",
              "isExpression": false,
              "asc": true,
              "nulls": "last"
            }
          ],
          "isUnique": false,
          "concurrently": false,
          "method": "btree",
          "with": {}
        }
      },
      "foreignKeys": {
        "submissions_user_id_users_id_fk": {
          "name": "submissions_user_id_users_id_fk",
          "tableFrom": "submissions",
          "tableTo": "users",
          "columnsFrom": [
            "user_id"
          ],
          "columnsTo": [
            "id"
          ],
          "onDelete": "cascade",
          "onUpdate": "no action"
        }
      },
      "compositePrimaryKeys": {},
      "uniqueConstraints": {},
      "policies": {},
      "checkConstraints": {},
      "isRLSEnabled": false
    },
    "public.transcript_segments": {
      "name": "transcript_segments",
      "schema": "",
      "columns": {
        "id": {
          "name": "id",
          "type": "serial",
          "primaryKey": true,
          "notNull": true
        },
        "call_session_id": {
          "name": "call_session_id",
          "type": "text",
          "primaryKey": false,
          "notNull": true
        },
        "speaker": {
          "name": "speaker",
          "type": "text",
          "primaryKey": false,
          "notNull": true
        },
        "text": {
          "name": "text",
          "type": "text",
          "primaryKey": false,
          "notNull": true
        },
        "timestamp": {
          "name": "timestamp",
          "type": "timestamp",
          "primaryKey": false,
          "notNull": true
        },
        "confidence": {
          "name": "confidence",
          "type": "real",
          "primaryKey": false,
          "notNull": false
        },
        "created_at": {
          "name": "created_at",
          "type": "timestamp",
          "primaryKey": false,
          "notNull": true,
          "default": "now()"
        }
      },
      "indexes": {
        "transcript_segments_call_session_id_idx": {
          "name": "transcript_segments_call_session_id_idx",
          "columns": [
            {
              "expression": "call_session_id",
              "isExpression": false,
              "asc": true,
              "nulls": "last"
            }
          ],
          "isUnique": false,
          "concurrently": false,
          "method": "btree",
          "with": {}
        },
        "transcript_segments_timestamp_idx": {
          "name": "transcript_segments_timestamp_idx",
          "columns": [
            {
              "expression": "timestamp",
              "isExpression": false,
              "asc": true,
              "nulls": "last"
            }
          ],
          "isUnique": false,
          "concurrently": false,
          "method": "btree",
          "with": {}
        }
      },
      "foreignKeys": {
        "transcript_segments_call_session_id_call_sessions_id_fk": {
          "name": "transcript_segments_call_session_id_call_sessions_id_fk",
          "tableFrom": "transcript_segments",
          "tableTo": "call_sessions",
          "columnsFrom": [
            "call_session_id"
          ],
          "columnsTo": [
            "id"
          ],
          "onDelete": "cascade",
          "onUpdate": "no action"
        }
      },
      "compositePrimaryKeys": {},
      "uniqueConstraints": {},
      "policies": {},
      "checkConstraints": {},
      "isRLSEnabled": false
    },
    "public.users": {
      "name": "users",
      "schema": "",
      "columns": {
        "id": {
          "name": "id",
          "type": "text",
          "primaryKey": true,
          "notNull": true
        },
        "email": {
          "name": "email",
          "type": "text",
          "primaryKey": false,
          "notNull": true
        },
        "name": {
          "name": "name",
          "type": "text",
          "primaryKey": false,
          "notNull": false
        },
        "avatar": {
          "name": "avatar",
          "type": "text",
          "primaryKey": false,
          "notNull": false
        },
        "created_at": {
          "name": "created_at",
          "type": "timestamp",
          "primaryKey": false,
          "notNull": true,
          "default": "now()"
        },
        "updated_at": {
          "name": "updated_at",
          "type": "timestamp",
          "primaryKey": false,
          "notNull": true,
          "default": "now()"
        }
      },
      "indexes": {},
      "foreignKeys": {},
      "compositePrimaryKeys": {},
      "uniqueConstraints": {
        "users_email_unique": {
          "name": "users_email_unique",
          "nullsNotDistinct": false,
          "columns": [
            "email"
          ]
        }
      },
      "policies": {},
      "checkConstraints": {},
      "isRLSEnabled": false
    }
  },
  "enums": {},
  "schemas": {},
  "sequences": {},
  "roles": {},
  "policies": {},
  "views": {},
  "_meta": {
    "columns": {},
    "schemas": {},
    "tables": {}
  }
}